pydantic_quantlib/__init__.py
pydantic_quantlib/core.py
pydantic_quantlib-0.3.0.dist-info/AUTHORS.rst
pydantic_quantlib-0.3.0.dist-info/LICENSE
pydantic_quantlib-0.3.0.dist-info/METADATA
pydantic_quantlib-0.3.0.dist-info/WHEEL
pydantic_quantlib-0.3.0.dist-info/top_level.txt
pydantic_quantlib-0.3.0.dist-info/RECORD
