Metadata-Version: 2.1
Name: pydantic-quantlib
Version: 0.3.0
Summary: QuantLib Python Objects with Typing
Home-page: https://github.com/gecBurton/pydantic-quantlib
Author: George EC Burton
Author-email: g.e.c.burton@gmail.com
License: MIT license
Keywords: pydantic_quantlib
Platform: UNKNOWN
Classifier: Development Status :: 2 - Pre-Alpha
Classifier: Intended Audience :: Developers
Classifier: License :: OSI Approved :: MIT License
Classifier: Natural Language :: English
Classifier: Programming Language :: Python :: 3
Classifier: Programming Language :: Python :: 3.8
Classifier: Programming Language :: Python :: 3.9
Requires-Python: >=3.8
Requires-Dist: pydantic
Requires-Dist: QuantLib (>=1.20)
